{
  "nested": {
    "openbts": {
      "nested": {
        "locations": {
          "nested": {
            "LocationStation": {
              "fields": {
                "id": {
                  "type": "int32",
                  "id": 1
                },
                "station_id": {
                  "type": "string",
                  "id": 2
                },
                "notes": {
                  "type": "string",
                  "id": 3
                },
                "extra_address": {
                  "type": "string",
                  "id": 4
                },
                "updatedAt": {
                  "type": "string",
                  "id": 5
                },
                "createdAt": {
                  "type": "string",
                  "id": 6
                },
                "is_confirmed": {
                  "type": "bool",
                  "id": 7
                },
                "status": {
                  "type": "StationStatus",
                  "id": 8
                },
                "operator": {
                  "type": "Operator",
                  "id": 9
                },
                "cells": {
                  "rule": "repeated",
                  "type": "openbts.stations.CellWithoutDetails",
                  "id": 10
                },
                "extra_identificators": {
                  "type": "openbts.stations.ExtraIdentificators",
                  "id": 11
                }
              }
            },
            "Location": {
              "fields": {
                "id": {
                  "type": "int32",
                  "id": 1
                },
                "city": {
                  "type": "string",
                  "id": 2
                },
                "address": {
                  "type": "string",
                  "id": 3
                },
                "latitude": {
                  "type": "double",
                  "id": 4
                },
                "longitude": {
                  "type": "double",
                  "id": 5
                },
                "updatedAt": {
                  "type": "string",
                  "id": 6
                },
                "createdAt": {
                  "type": "string",
                  "id": 7
                },
                "region": {
                  "type": "Region",
                  "id": 8
                },
                "stations": {
                  "rule": "repeated",
                  "type": "LocationStation",
                  "id": 9
                }
              }
            },
            "LocationsResponse": {
              "fields": {
                "data": {
                  "rule": "repeated",
                  "type": "Location",
                  "id": 1
                },
                "totalCount": {
                  "type": "int32",
                  "id": 2
                }
              }
            },
            "LocationResponse": {
              "fields": {
                "data": {
                  "type": "Location",
                  "id": 1
                }
              }
            }
          }
        },
        "StationStatus": {
          "values": {
            "published": 0,
            "inactive": 1,
            "pending": 2
          }
        },
        "Operator": {
          "fields": {
            "id": {
              "type": "int32",
              "id": 1
            },
            "name": {
              "type": "string",
              "id": 2
            },
            "full_name": {
              "type": "string",
              "id": 3
            },
            "parent_id": {
              "type": "int32",
              "id": 4
            },
            "mnc": {
              "type": "int32",
              "id": 5
            }
          }
        },
        "Region": {
          "fields": {
            "id": {
              "type": "int32",
              "id": 1
            },
            "name": {
              "type": "string",
              "id": 2
            },
            "code": {
              "type": "string",
              "id": 3
            }
          }
        },
        "Rat": {
          "values": {
            "GSM": 0,
            "CDMA": 1,
            "UMTS": 2,
            "LTE": 3,
            "NR": 4,
            "IOT": 5
          }
        },
        "Duplex": {
          "values": {
            "FDD": 0,
            "TDD": 1
          }
        },
        "BandVariant": {
          "values": {
            "commercial": 0,
            "railway": 1
          }
        },
        "Band": {
          "fields": {
            "id": {
              "type": "int32",
              "id": 1
            },
            "value": {
              "type": "int32",
              "id": 2
            },
            "rat": {
              "type": "Rat",
              "id": 3
            },
            "name": {
              "type": "string",
              "id": 4
            },
            "duplex": {
              "type": "Duplex",
              "id": 5
            },
            "variant": {
              "type": "BandVariant",
              "id": 6
            }
          }
        },
        "stations": {
          "nested": {
            "StationCell": {
              "fields": {
                "id": {
                  "type": "int32",
                  "id": 1
                },
                "rat": {
                  "type": "Rat",
                  "id": 2
                },
                "notes": {
                  "type": "string",
                  "id": 3
                },
                "band": {
                  "type": "Band",
                  "id": 4
                },
                "is_confirmed": {
                  "type": "bool",
                  "id": 5
                },
                "details": {
                  "type": "google.protobuf.Struct",
                  "id": 8
                },
                "updatedAt": {
                  "type": "string",
                  "id": 6
                },
                "createdAt": {
                  "type": "string",
                  "id": 7
                }
              }
            },
            "NRType": {
              "values": {
                "unknown": 0,
                "nsa": 1,
                "sa": 2
              }
            },
            "Cell": {
              "fields": {
                "id": {
                  "type": "int32",
                  "id": 1
                },
                "station_id": {
                  "type": "int32",
                  "id": 2
                },
                "rat": {
                  "type": "Rat",
                  "id": 3
                },
                "notes": {
                  "type": "string",
                  "id": 4
                },
                "band": {
                  "type": "Band",
                  "id": 5
                },
                "is_confirmed": {
                  "type": "bool",
                  "id": 6
                },
                "details": {
                  "type": "google.protobuf.Struct",
                  "id": 7
                },
                "updatedAt": {
                  "type": "string",
                  "id": 8
                },
                "createdAt": {
                  "type": "string",
                  "id": 9
                }
              }
            },
            "CellWithoutDetails": {
              "fields": {
                "id": {
                  "type": "int32",
                  "id": 1
                },
                "station_id": {
                  "type": "int32",
                  "id": 2
                },
                "rat": {
                  "type": "Rat",
                  "id": 3
                },
                "notes": {
                  "type": "string",
                  "id": 4
                },
                "band": {
                  "type": "Band",
                  "id": 5
                },
                "is_confirmed": {
                  "type": "bool",
                  "id": 6
                },
                "updatedAt": {
                  "type": "string",
                  "id": 8
                },
                "createdAt": {
                  "type": "string",
                  "id": 9
                }
              }
            },
            "ExtraIdentificators": {
              "fields": {
                "id": {
                  "type": "int32",
                  "id": 1
                },
                "networks_id": {
                  "type": "int32",
                  "id": 2
                },
                "networks_name": {
                  "type": "string",
                  "id": 3
                },
                "mno_name": {
                  "type": "string",
                  "id": 4
                },
                "updatedAt": {
                  "type": "string",
                  "id": 5
                },
                "createdAt": {
                  "type": "string",
                  "id": 6
                }
              }
            },
            "Station": {
              "fields": {
                "id": {
                  "type": "int32",
                  "id": 1
                },
                "station_id": {
                  "type": "string",
                  "id": 2
                },
                "notes": {
                  "type": "string",
                  "id": 3
                },
                "extra_address": {
                  "type": "string",
                  "id": 4
                },
                "cells": {
                  "rule": "repeated",
                  "type": "StationCell",
                  "id": 5
                },
                "extra_identificators": {
                  "type": "ExtraIdentificators",
                  "id": 6
                },
                "location": {
                  "type": "openbts.locations.Location",
                  "id": 7
                },
                "operator": {
                  "type": "Operator",
                  "id": 8
                },
                "is_confirmed": {
                  "type": "bool",
                  "id": 9
                },
                "updatedAt": {
                  "type": "string",
                  "id": 10
                },
                "createdAt": {
                  "type": "string",
                  "id": 11
                }
              }
            },
            "StationsResponse": {
              "fields": {
                "data": {
                  "rule": "repeated",
                  "type": "Station",
                  "id": 1
                },
                "totalCount": {
                  "type": "int32",
                  "id": 2
                }
              }
            },
            "StationResponse": {
              "fields": {
                "data": {
                  "type": "Station",
                  "id": 1
                }
              }
            },
            "CellsResponse": {
              "fields": {
                "data": {
                  "rule": "repeated",
                  "type": "Cell",
                  "id": 1
                }
              }
            },
            "CellResponse": {
              "fields": {
                "data": {
                  "type": "Cell",
                  "id": 1
                }
              }
            }
          }
        }
      }
    },
    "google": {
      "nested": {
        "protobuf": {
          "nested": {
            "Timestamp": {
              "fields": {
                "seconds": {
                  "type": "int64",
                  "id": 1
                },
                "nanos": {
                  "type": "int32",
                  "id": 2
                }
              }
            },
            "Struct": {
              "fields": {
                "fields": {
                  "keyType": "string",
                  "type": "Value",
                  "id": 1
                }
              }
            },
            "Value": {
              "oneofs": {
                "kind": {
                  "oneof": ["nullValue", "numberValue", "stringValue", "boolValue", "structValue", "listValue"]
                }
              },
              "fields": {
                "nullValue": {
                  "type": "NullValue",
                  "id": 1
                },
                "numberValue": {
                  "type": "double",
                  "id": 2
                },
                "stringValue": {
                  "type": "string",
                  "id": 3
                },
                "boolValue": {
                  "type": "bool",
                  "id": 4
                },
                "structValue": {
                  "type": "Struct",
                  "id": 5
                },
                "listValue": {
                  "type": "ListValue",
                  "id": 6
                }
              }
            },
            "NullValue": {
              "values": {
                "NULL_VALUE": 0
              }
            },
            "ListValue": {
              "fields": {
                "values": {
                  "rule": "repeated",
                  "type": "Value",
                  "id": 1
                }
              }
            }
          }
        }
      }
    }
  }
}
